kirxa_testing_packaging/__init__.py
kirxa_testing_packaging/main.py
kirxa_testing_packaging-0.1.dist-info/METADATA
kirxa_testing_packaging-0.1.dist-info/WHEEL
kirxa_testing_packaging-0.1.dist-info/top_level.txt
kirxa_testing_packaging-0.1.dist-info/RECORD
