Metadata-Version: 2.1
Name: kirxa-testing-packaging
Version: 0.1
Requires-Dist: matplotlib (>=3.0.0)
